pydatabridge/__init__.py
pydatabridge/app.py
pydatabridge/command.py
pydatabridge/command_queue_invoker.py
pydatabridge/data_access_adapter.py
pydatabridge/data_access_criteria.py
pydatabridge/data_access_model.py
pydatabridge/data_access_model_pointer.py
pydatabridge/sync_command.py
pydatabridge/sync_command_queue_invoker.py
pydatabridge/sync_strategy.py
pydatabridge/sync_strategy_incremental.py
pydatabridge/sync_strategy_incremental_pulling.py
pydatabridge/sync_strategy_incremental_pushing.py
pydatabridge/exceptions/__init__.py
pydatabridge/exceptions/adapter_exception.py
pydatabridge/services/__init__.py
pydatabridge/services/dependency_sorter.py
pydatabridge/services/entity_adapter_id_index_manager.py
pydatabridge/services/sync_time_manager.py
pyDataBridge-0.0.1.dist-info/LICENSE
pyDataBridge-0.0.1.dist-info/METADATA
pyDataBridge-0.0.1.dist-info/WHEEL
pyDataBridge-0.0.1.dist-info/top_level.txt
pyDataBridge-0.0.1.dist-info/RECORD
