Metadata-Version: 2.1
Name: pyDataBridge
Version: 0.0.1
Summary: A data synchronization framework for python
Author-email: "J. Alexánder Alzate Olaya" <it@jaalzateolaya.com>
License: MIT License
Project-URL: Homepage, https://gitlab.com/jaalzateolaya/pydatabridge
Project-URL: Bug Tracker, https://gitlab.com/jaalzateolaya/pydatabridge/-/issues
Keywords: ETL,Data Synchronization
Classifier: Development Status :: 4 - Beta
Classifier: Intended Audience :: Developers
Classifier: License :: OSI Approved :: MIT License
Classifier: Operating System :: OS Independent
Classifier: Programming Language :: Python :: 3
Classifier: Topic :: Software Development :: Libraries :: Python Modules
Requires-Python: >=3.7
License-File: LICENSE
Requires-Dist: dependency-injector >=4.41
Requires-Dist: pypika-git
